{
  "name": "orthotenkey",
  "vendorId": "0xFEED",
  "productId": "0x6061",
    "matrix": {
        "rows": 5,
        "cols": 5
    },
    "layouts": {
        "labels": [],
        "keymap":[
      ["0,0","0,1","0,2","0,3","0,4"],
      ["1,0","1,1","1,2","1,3"],
      ["2,0","2,1","2,2","2,3","2,4"],
      ["3,0","3,1","3,2","3,3"],
      ["4,0","4,1","4,2","4,3","4,4"]
        ]
    },
  "vial": {
    "keyboard_uid": [95, 113, 201, 170, 17, 240, 248, 232],
    "unlock_combo": {
      "rows": [0, 0],
      "cols": [0, 1]
    }
    }
}
